promptl_ai/__init__.py
promptl_ai/py.typed
promptl_ai/bindings/__init__.py
promptl_ai/bindings/chains.py
promptl_ai/bindings/errors.py
promptl_ai/bindings/promptl.py
promptl_ai/bindings/prompts.py
promptl_ai/bindings/types.py
promptl_ai/bindings/adapters/__init__.py
promptl_ai/bindings/adapters/anthropic.py
promptl_ai/bindings/adapters/openai.py
promptl_ai/resources/promptl.wasm
promptl_ai/rpc/__init__.py
promptl_ai/rpc/client.py
promptl_ai/rpc/errors.py
promptl_ai/rpc/payloads.py
promptl_ai/rpc/types.py
promptl_ai/util/__init__.py
promptl_ai/util/utils.py
promptl_ai/version/__init__.py
promptl_ai/version/version.py
promptl_ai-1.2.0.dist-info/METADATA
promptl_ai-1.2.0.dist-info/WHEEL
promptl_ai-1.2.0.dist-info/licenses/LICENSE
promptl_ai-1.2.0.dist-info/RECORD
