Metadata-Version: 2.4
Name: promptl-ai
Version: 1.2.0
Summary: PromptL bindings for Python
Project-URL: repository, https://github.com/latitude-dev/promptl-py
Project-URL: homepage, https://github.com/latitude-dev/promptl-py#readme
Project-URL: documentation, https://docs.latitude.so/promptl
Author-email: Latitude Data SL <hello@latitude.so>
Maintainer-email: Latitude Data SL <hello@latitude.so>
License-Expression: MIT
License-File: LICENSE
Requires-Python: <3.14,>=3.9
Requires-Dist: pydantic>=2.11.9
Requires-Dist: typing-extensions>=4.15.0
Requires-Dist: wasmtime>=36.0.0
